{
  "1": {
    "Grid": [
      ["NV", "NV"],
      ["NV", "NV"]
    ],
    "Message": 1,
    "Pieces": [
      { "Grid": [["N2", "N2"]] },
      { "Grid": [["N1"]] },
      { "Grid": [["N4"]] }
    ],
    "Filled_grid": [
      [1, 1],
      [2, 3]
    ]
  },
  "2": {
    "Grid": [
      ["NV", "NV", "NV"],
      ["NV", "NV", "NV"],
      ["NV", "NV", "NV"]
    ],
    "Message": 2,
    "Pieces": [
      {
        "Grid": [
          ["N4", "N4", "N4"],
          ["N4", "NV", "NV"]
        ]
      },
      {
        "Grid": [
          ["N3", "N3"],
          ["N3", "N3"]
        ]
      },
      { "Grid": [["N2"]] }
    ],
    "Filled_grid": [
      [1, 1, 1],
      [1, 2, 2],
      [3, 2, 2]
    ]
  },
  "3": {
    "Grid": [
      ["H0", "NV", "NV"],
      ["H0", "NV", "NV"],
      ["H0", "H0", "NV"]
    ],
    "Message": 3,
    "Pieces": [
      {
        "Grid": [
          ["N1", "N1"],
          ["N1", "NV"]
        ]
      },
      { "Grid": [["N3"], ["N3"]] }
    ],
    "Filled_grid": [
      [null, 1, 1],
      [null, 1, 2],
      [null, null, 2]
    ]
  },
  "4": {
    "Grid": [
      ["H0", "NV", "NV", "NV"],
      ["NV", "NV", "NV", "NV"],
      ["NV", "NV", "NV", "NV"],
      ["NV", "NV", "NV", "NV"]
    ],
    "Message": 4,
    "Pieces": [
      {
        "Grid": [
          ["N1", "N1"],
          ["N1", "NV"],
          ["N1", "NV"],
          ["N1", "NV"]
        ]
      },
      { "Grid": [["N2", "N2"]] },
      {
        "Grid": [
          ["N3", "N3"],
          ["N3", "N3"],
          ["N3", "N3"],
          ["N3", "N3"]
        ]
      }
    ],
    "Filled_grid": [
      [null, 3, 2, 2],
      [4, 3, 2, 2],
      [4, 3, 2, 2],
      [3, 3, 2, 2]
    ]
  },
  "5": {
    "Grid": [
      ["M3", "M3", "M3", "M3"],
      ["M2", "M2", "M3", "M3"],
      ["M2", "M2", "M2", "M3"],
      ["M2", "M2", "M2", "M2"]
    ],
    "Message": 5,
    "Pieces": [
      { "Grid": [["N3", "N3", "N3", "N3"]] },
      {
        "Grid": [
          ["N3", "N3"],
          ["NV", "N3"]
        ]
      },
      {
        "Grid": [
          ["N2", "N2"],
          ["N2", "NV"],
          ["N2", "NV"]
        ]
      },
      {
        "Grid": [
          ["N2", "N2", "NV"],
          ["N2", "N2", "N2"]
        ]
      }
    ],
    "Filled_grid": [
      [2, 2, 2, 2],
      [3, 3, 1, 1],
      [3, 4, 4, 1],
      [3, 4, 4, 4]
    ]
  },
  "6": {
    "Grid": [
      ["NV", "NV", "NV", "NV"],
      ["NV", "NV", "NV", "NV"],
      ["NV", "NV", "NV", "NV"],
      ["NV", "NV", "NV", "NV"]
    ],
    "Message": 6,
    "Pieces": [
      { "Grid": [["N2", "N2", "N2", "N2"]] },
      { "Grid": [["N4"], ["N4"], ["N4"]] },
      {
        "Grid": [
          ["NV", "NV", "N5"],
          ["N5", "N5", "N5"]
        ]
      },
      {
        "Grid": [
          ["N1", "N1", "N1"],
          ["N1", "N1", "NV"]
        ]
      }
    ],
    "Filled_grid": [
      [1, 1, 1, 1],
      [2, 4, 4, 4],
      [2, 4, 4, 3],
      [2, 3, 3, 3]
    ]
  },
  "7": {
    "Grid": [
      ["H0", "NV", "NV", "NV"],
      ["NV", "H0", "NV", "NV"],
      ["NV", "NV", "H0", "NV"],
      ["NV", "NV", "NV", "NV"]
    ],
    "Pieces": [
      { "Grid": [["N2"]] },
      { "Grid": [["N6"], ["N6"], ["N6"]] },
      {
        "Grid": [
          ["N1", "N1"],
          ["N1", "NV"]
        ]
      },
      { "Grid": [["N2"]] },
      { "Grid": [["N5", "N5", "N5"]] },
      { "Grid": [["N3"], ["N3"]] }
    ],
    "Filled_grid": [
      [null, 6, 3, 3],
      [1, null, 3, 4],
      [1, 5, null, 4],
      [1, 2, 2, 2]
    ]
  },
  "8": {
    "Grid": [
      ["NV", "NV", "NV", "NV"],
      ["NV", "NV", "NV", "NV"],
      ["NV", "NV", "NV", "NV"],
      ["NV", "NV", "NV", "NV"]
    ],
    "Pieces": [
      {
        "Grid": [
          ["N2", "NV"],
          ["N2", "NV"],
          ["N1", "N1"]
        ]
      },
      {
        "Grid": [
          ["N6", "N6"],
          ["N5", "NV"],
          ["N5", "NV"]
        ]
      },
      { "Grid": [["N1"], ["N2"], ["N5"], ["N3"]] },
      {
        "Grid": [
          ["NV", "N6"],
          ["N3", "N3"],
          ["N5", "NV"]
        ]
      }
    ],
    "Filled_grid": [
      [3, 3, 2, 1],
      [3, 2, 2, 1],
      [3, 2, 4, 1],
      [4, 4, 4, 1]
    ]
  },
  "9": {
    "Grid": [
      ["NV", "NV", "NV", "NV"],
      ["NV", "NV", "H0", "NV"],
      ["NV", "H0", "NV", "NV"],
      ["NV", "NV", "NV", "H0"]
    ],
    "Pieces": [
      { "Grid": [["N3"], ["N3"]] },
      { "Grid": [["N4"], ["N4"], ["N4"]] },
      {
        "Grid": [
          ["NV", "N2", "N2"],
          ["N2", "N2", "NV"]
        ]
      },
      { "Grid": [["N2"]] },
      { "Grid": [["N1", "N1", "N1"]] }
    ],
    "Filled_grid": [
      [3, 3, 3, 4],
      [1, 5, null, 4],
      [1, null, 2, 2],
      [1, 2, 2, null]
    ]
  },
  "10": {
    "Grid": [
      ["M5", "M5", "M5", "M5", "M5"],
      ["M4", "M4", "M5", "M5", "M5"],
      ["M4", "M4", "M4", "M4", "M5"],
      ["M4", "M4", "M4", "M4", "M5"],
      ["M4", "M4", "M4", "M4", "M4"]
    ],
    "Pieces": [
      { "Grid": [["N5"]] },
      { "Grid": [["N5"], ["N5"], ["N4"]] },
      {
        "Grid": [
          ["NV", "N4", "N4"],
          ["N5", "N5", "NV"]
        ]
      },
      { "Grid": [["N5"], ["N5"], ["N5"], ["N5"], ["N5"]] },
      {
        "Grid": [
          ["N4", "NV"],
          ["N4", "N4"],
          ["N4", "N4"]
        ]
      },
      { "Grid": [["N4", "N4", "N4"]] },
      { "Grid": [["N4", "N4", "N4", "N4"]] }
    ],
    "Filled_grid": [
      [1, 1, 1, 1, 1],
      [5, 6, 7, 3, 3],
      [5, 6, 3, 3, 2],
      [5, 6, 4, 4, 2],
      [5, 4, 4, 4, 2]
    ]
  },
  "11": {
    "Grid": [
      ["NV", "NV", "NV", "NV", "NV"],
      ["NV", "NV", "NV", "NV", "NV"],
      ["NV", "NV", "NV", "NV", "NV"],
      ["NV", "NV", "NV", "NV", "NV"]
    ],
    "Pieces": [
      { "Grid": [["N4"], ["N4"], ["N4"]] },
      {
        "Grid": [
          ["N2", "N2", "N2"],
          ["N2", "N2", "N2"]
        ]
      },
      {
        "Grid": [
          ["N5", "N5"],
          ["N5", "N5"],
          ["N5", "N5"]
        ]
      },
      {
        "Grid": [
          ["NV", "NV", "NV", "N1"],
          ["N1", "N1", "N1", "N1"]
        ]
      }
    ],
    "Filled_grid": [
      [1, 2, 2, 3, 3],
      [1, 2, 2, 3, 3],
      [1, 2, 2, 3, 3],
      [1, 1, 4, 4, 4]
    ]
  },
  "12": {
    "Grid": [
      ["NV", "NV", "NV", "NV", "NV"],
      ["NV", "NV", "NV", "NV", "NV"],
      ["NV", "NV", "NV", "NV", "NV"],
      ["NV", "NV", "NV", "NV", "NV"],
      ["NV", "NV", "NV", "NV", "NV"]
    ],
    "Pieces": [
      {
        "Grid": [
          ["N1", "N1"],
          ["N1", "NV"],
          ["N1", "NV"],
          ["N1", "NV"]
        ]
      },
      {
        "Grid": [
          ["N2", "N2"],
          ["N2", "NV"],
          ["N2", "NV"],
          ["N2", "NV"]
        ]
      },
      {
        "Grid": [
          ["N5", "N5", "NV"],
          ["N5", "N5", "N5"]
        ]
      },
      {
        "Grid": [
          ["N3", "NV"],
          ["N3", "N3"]
        ]
      },
      {
        "Grid": [
          ["N3", "N3"],
          ["N3", "NV"]
        ]
      },
      {
        "Grid": [
          ["N6", "N6"],
          ["N6", "NV"],
          ["N6", "NV"]
        ]
      }
    ],
    "Filled_grid": [
      [1, 1, 5, 6, 6],
      [1, 2, 5, 5, 6],
      [1, 2, 4, 4, 4],
      [1, 2, 3, 3, 4],
      [2, 2, 3, 3, 3]
    ]
  },
  "13": {
    "Grid": [
      ["H0", "NV", "NV", "NV", "NV"],
      ["H0", "NV", "NV", "H0", "H0"],
      ["NV", "H0", "H0", "NV", "NV"],
      ["NV", "NV", "H0", "NV", "NV"],
      ["NV", "NV", "NV", "NV", "H0"]
    ],
    "Pieces": [
      { "Grid": [["N2", "N2"]] },
      {
        "Grid": [
          ["N2", "NV"],
          ["N2", "NV"],
          ["NV", "N2"]
        ]
      },
      { "Grid": [["N1"]] },
      { "Grid": [["N4"], ["N4"], ["N4"]] },
      {
        "Grid": [
          ["N3", "NV"],
          ["N3", "NV"],
          ["NV", "NV"],
          ["NV", "N3"],
          ["NV", "N3"]
        ]
      },
      {
        "Grid": [
          ["NV", "N5", "N5"],
          ["N5", "N5", "NV"]
        ]
      }
    ],
    "Filled_grid": [
      [null, 5, 5, 5, 6],
      [null, 1, 1, null, null],
      [1, null, null, 2, 2],
      [2, 2, null, 3, 3],
      [4, 4, 3, 3, null]
    ]
  },
  "14": {
    "Grid": [
      ["NV", "NV", "NV", "NV"],
      ["NV", "NV", "NV", "NV"],
      ["NV", "NV", "NV", "NV"],
      ["NV", "NV", "NV", "NV"],
      ["NV", "NV", "NV", "NV"]
    ],
    "Pieces": [
      {
        "Grid": [
          ["N5", "N5"],
          ["N5", "NV"],
          ["N5", "NV"],
          ["N5", "NV"]
        ]
      },
      {
        "Grid": [
          ["N6", "N6"],
          ["N6", "N6"],
          ["N6", "N6"]
        ]
      },
      {
        "Grid": [
          ["N2", "N2"],
          ["N2", "NV"]
        ]
      },
      { "Grid": [["N6", "N6", "N6"]] },
      {
        "Grid": [
          ["N1", "N1"],
          ["N1", "NV"]
        ]
      }
    ],
    "Filled_grid": [
      [1, 1, 1, 1],
      [3, 3, 3, 1],
      [3, 3, 3, 6],
      [4, 4, 5, 6],
      [4, 5, 5, 6]
    ]
  },
  "15": {
    "Grid": [
      ["NV", "NV", "NV", "NV", "NV"],
      ["NV", "NV", "H0", "NV", "NV"],
      ["NV", "H0", "H0", "H0", "NV"],
      ["NV", "NV", "H0", "NV", "NV"],
      ["NV", "NV", "NV", "NV", "NV"]
    ],
    "Pieces": [
      {
        "Grid": [
          ["NV", "N3"],
          ["N3", "N3"]
        ]
      },
      { "Grid": [["N6"]] },
      { "Grid": [["N2", "N2", "N2"]] },
      {
        "Grid": [
          ["N4", "NV"],
          ["N4", "N4"],
          ["N4", "NV"]
        ]
      },
      {
        "Grid": [
          ["NV", "N2"],
          ["N2", "N2"]
        ]
      },
      {
        "Grid": [
          ["N1", "NV"],
          ["N1", "N1"]
        ]
      },
      {
        "Grid": [
          ["NV", "NV", "N2"],
          ["NV", "N2", "NV"],
          ["N2", "NV", "NV"]
        ]
      }
    ],
    "Filled_grid": [
      [5, 6, 6, 6, 4],
      [5, 5, null, 4, 4],
      [1, null, null, null, 2],
      [1, 1, null, 2, 3],
      [1, 7, 2, 3, 3]
    ]
  },
  "16": {
    "Grid": [
      ["NV", "NV", "NV", "NV", "H0"],
      ["NV", "NV", "NV", "NV", "NV"],
      ["NV", "NV", "NV", "NV", "NV"],
      ["NV", "NV", "NV", "NV", "NV"],
      ["H0", "NV", "NV", "NV", "H0"]
    ],
    "Pieces": [
      {
        "Grid": [
          ["N5", "NV"],
          ["N5", "N5"]
        ]
      },
      {
        "Grid": [
          ["NV", "NV", "N3"],
          ["NV", "N3", "N3"],
          ["N3", "N3", "NV"]
        ]
      },
      { "Grid": [["N3"]] },
      {
        "Grid": [
          ["NV", "N6"],
          ["N6", "N6"]
        ]
      },
      {
        "Grid": [
          ["N2", "NV", "NV"],
          ["NV", "N2", "NV"],
          ["N2", "NV", "N2"]
        ]
      },
      {
        "Grid": [
          ["NV", "N1"],
          ["N1", "NV"]
        ]
      },
      {
        "Grid": [
          ["N2", "NV", "NV", "NV"],
          ["NV", "N2", "NV", "NV"],
          ["NV", "NV", "N2", "NV"],
          ["NV", "NV", "NV", "N2"]
        ]
      }
    ],
    "Filled_grid": [
      [6, 6, 5, 5, null],
      [6, 3, 5, 3, 2],
      [7, 4, 3, 2, 1],
      [4, 3, 2, 1, 1],
      [null, 2, 1, 1, null]
    ]
  },
  "17": {
    "Grid": [
      ["NV", "NV", "NV", "NV", "NV"],
      ["NV", "NV", "NV", "NV", "NV"],
      ["NV", "NV", "NV", "NV", "NV"],
      ["NV", "NV", "NV", "NV", "NV"],
      ["NV", "NV", "NV", "NV", "NV"]
    ],
    "Pieces": [
      {
        "Grid": [
          ["N4", "N4", "N4"],
          ["N4", "NV", "NV"]
        ]
      },
      {
        "Grid": [
          ["N5", "N5", "N5"],
          ["N5", "NV", "NV"]
        ]
      },
      {
        "Grid": [
          ["N3", "N3", "N3"],
          ["N3", "NV", "NV"]
        ]
      },
      {
        "Grid": [
          ["NV", "N2"],
          ["NV", "N2"],
          ["N2", "N2"]
        ]
      },
      {
        "Grid": [
          ["NV", "NV", "N2"],
          ["N2", "N2", "N2"]
        ]
      },
      {
        "Grid": [
          ["NV", "NV", "N3"],
          ["N3", "N3", "N3"]
        ]
      },
      { "Grid": [["N1"]] }
    ],
    "Filled_grid": [
      [1, 1, 1, 3, 2],
      [1, 3, 3, 3, 2],
      [6, 6, 6, 2, 2],
      [6, 5, 5, 5, 4],
      [7, 5, 4, 4, 4]
    ]
  },
  "18": {
    "Grid": [
      ["NV", "NV", "NV", "NV", "NV"],
      ["NV", "NV", "NV", "NV", "NV"],
      ["NV", "NV", "NV", "NV", "NV"],
      ["NV", "NV", "NV", "NV", "NV"],
      ["NV", "NV", "NV", "NV", "NV"]
    ],
    "Pieces": [
      {
        "Grid": [
          ["NV", "N6", "N6"],
          ["N6", "N6", "NV"]
        ]
      },
      {
        "Grid": [
          ["N3", "N3"],
          ["N3", "N3"]
        ]
      },
      {
        "Grid": [
          ["N4", "N4"],
          ["N4", "N4"],
          ["N4", "NV"]
        ]
      },
      { "Grid": [["N2", "N2", "N2"]] },
      { "Grid": [["N4"]] },
      {
        "Grid": [
          ["N5", "N5", "N5"],
          ["NV", "NV", "N5"]
        ]
      },
      {
        "Grid": [
          ["NV", "NV", "N1"],
          ["N1", "N1", "N1"]
        ]
      }
    ],
    "Filled_grid": [
      [1, 1, 8, 8, 8],
      [1, 1, 7, 7, 8],
      [1, 7, 7, 13, 10],
      [11, 11, 10, 10, 10],
      [11, 11, 12, 12, 12]
    ]
  },
  "19": {
    "Grid": [
      ["NV", "NV", "NV", "NV", "NV"],
      ["NV", "NV", "H0", "NV", "NV"],
      ["NV", "NV", "H0", "NV", "NV"],
      ["NV", "NV", "H0", "NV", "NV"],
      ["NV", "NV", "NV", "NV", "NV"]
    ],
    "Pieces": [
      {
        "Grid": [
          ["NV", "N1"],
          ["NV", "N1"],
          ["N1", "N1"]
        ]
      },
      { "Grid": [["N6"]] },
      {
        "Grid": [
          ["N3", "NV"],
          ["N3", "N3"]
        ]
      },
      { "Grid": [["N2"], ["N2"]] },
      {
        "Grid": [
          ["N4", "N4"],
          ["NV", "N4"]
        ]
      },
      {
        "Grid": [
          ["N5", "N5"],
          ["NV", "N5"],
          ["N5", "N5"]
        ]
      },
      { "Grid": [["N2", "N2", "N2", "N2"]] }
    ],
    "Filled_grid": [
      [6, 5, 5, 5, 5],
      [6, 6, null, 3, 3],
      [1, 1, null, 2, 3],
      [7, 1, null, 2, 4],
      [1, 1, 2, 2, 4]
    ]
  },
  "20": {
    "Grid": [
      ["M6", "M1", "M1", "M1", "M6"],
      ["M6", "M3", "M1", "M3", "M6"],
      ["M6", "M3", "M6", "M3", "M3"],
      ["M3", "M1", "M3", "M1", "M3"],
      ["M1", "M3", "M6", "M6", "M3"]
    ],
    "Pieces": [
      { "Grid": [["N6", "N1"]] },
      {
        "Grid": [
          ["NV", "N6"],
          ["N3", "NV"]
        ]
      },
      { "Grid": [["N6", "N3"]] },
      {
        "Grid": [
          ["NV", "N1"],
          ["N1", "N3"]
        ]
      },
      {
        "Grid": [
          ["N6", "N3"],
          ["N6", "N3"]
        ]
      },
      {
        "Grid": [
          ["N1", "N1"],
          ["N1", "NV"]
        ]
      },
      {
        "Grid": [
          ["N3", "NV", "NV"],
          ["N6", "N6", "N3"]
        ]
      },
      {
        "Grid": [
          ["NV", "N6"],
          ["NV", "N3"],
          ["N1", "N3"]
        ]
      },
      { "Grid": [["N3"]] }
    ],
    "Filled_grid": [
      [3, 3, 1, 1, 9],
      [2, 2, 1, 9, 5],
      [2, 2, 6, 6, 5],
      [8, 7, 4, 5, 5],
      [7, 7, 4, 4, 4]
    ]
  },
  "21": {
    "Grid": [
      ["NV", "NV", "H0", "H0"],
      ["NV", "NV", "NV", "NV"],
      ["NV", "BNV", "BNV", "NV"],
      ["NV", "NV", "NV", "NV"],
      ["NV", "NV", "NV", "NV"]
    ],
    "Message": 34,
    "Pieces": [
      {
        "Grid": [
          ["N1", "N1"],
          ["N1", "NV"],
          ["N1", "NV"]
        ]
      },
      { "Grid": [["N3", "N3", "N3"]] },
      { "Grid": [["N4", "N4"]] },
      { "Grid": [["N2"], ["N2"], ["N2"]] },
      {
        "Grid": [
          ["NV", "N3", "N3"],
          ["N3", "N3", "N3"]
        ]
      },
      { "Grid": [["N2"]] }
    ],
    "Filled_grid": [
      [3, 3, null, null],
      [3, 2, 2, 2],
      [3, 6, 6, 1],
      [5, 4, 4, 1],
      [4, 4, 4, 1]
    ]
  },
  "22": {
    "Grid": [
      ["NV", "NV", "BH0", "BNV"],
      ["NV", "NV", "NV", "BNV"],
      ["BH0", "BH0", "NV", "NV"],
      ["BH0", "BH0", "NV", "NV"],
      ["NV", "NV", "BNV", "BH0"]
    ],
    "Pieces": [
      { "Grid": [["N2", "N2"]] },
      { "Grid": [["N3"]] },
      {
        "Grid": [
          ["N4", "N4"],
          ["N4", "N4"]
        ]
      },
      { "Grid": [["N2"], ["N2"]] },
      { "Grid": [["N5", "N5"]] },
      {
        "Grid": [
          ["N4", "N4"],
          ["N4", "NV"]
        ]
      }
    ],
    "Filled_grid": [
      [3, 2, null, 5],
      [3, 2, 2, 5],
      [null, null, 1, 1],
      [null, null, 1, 1],
      [4, 4, 6, null]
    ]
  },
  "23": {
    "Grid": [
      ["BH0", "BNV", "NV", "NV", "NV"],
      ["BNV", "BNV", "NV", "NV", "NV"],
      ["NV", "NV", "NV", "NV", "NV"],
      ["NV", "NV", "NV", "BH0", "BH0"],
      ["NV", "NV", "NV", "BNV", "BNV"]
    ],
    "Pieces": [
      {
        "Grid": [
          ["N4", "N4"],
          ["N4", "NV"]
        ]
      },
      { "Grid": [["N2"], ["N2"]] },
      {
        "Grid": [
          ["NV", "N1"],
          ["N1", "N1"]
        ]
      },
      {
        "Grid": [
          ["N6", "NV"],
          ["N6", "NV"],
          ["NV", "N6"]
        ]
      },
      {
        "Grid": [
          ["N1", "N1"],
          ["N1", "NV"]
        ]
      },
      { "Grid": [["N3"], ["N3"], ["N3"]] },
      { "Grid": [["N6"], ["N6"]] },
      { "Grid": [["N3", "N3"]] },
      { "Grid": [["N6"]] }
    ],
    "Filled_grid": [
      [null, 7, 1, 2, 2],
      [9, 7, 1, 2, 3],
      [4, 5, 5, 1, 3],
      [4, 5, 6, null, null],
      [4, 6, 6, 8, 8]
    ]
  },
  "24": {
    "Grid": [
      ["NV", "NV", "NV", "NV", "NV"],
      ["NV", "NV", "NV", "NV", "NV"],
      ["NV", "NV", "NV", "NV", "NV"],
      ["NV", "NV", "NV", "NV", "NV"],
      ["NV", "NV", "NV", "NV", "NV"]
    ],
    "Pieces": [
      {
        "Grid": [
          ["N1", "N1"],
          ["N1", "NV"],
          ["N1", "NV"],
          ["N1", "NV"]
        ]
      },
      {
        "Grid": [
          ["N2", "N2"],
          ["N2", "NV"],
          ["N2", "NV"],
          ["N2", "NV"]
        ]
      },
      {
        "Grid": [
          ["N5", "N5", "NV"],
          ["N5", "N5", "N5"]
        ]
      },
      {
        "Grid": [
          ["N3", "NV"],
          ["N3", "N3"],
          ["N3", "N3"],
          ["N3", "NV"]
        ]
      },
      {
        "Grid": [
          ["N6", "N6"],
          ["N6", "NV"],
          ["N6", "NV"]
        ]
      }
    ],
    "Filled_grid": [
      [1, 1, 4, 4, 4],
      [1, 2, 3, 4, 4],
      [1, 2, 3, 3, 5],
      [1, 2, 3, 3, 5],
      [2, 2, 3, 5, 5]
    ]
  },
  "25": {
    "Grid": [
      ["NV", "NV", "NV", "BM1", "BM1"],
      ["NV", "NV", "NV", "BM2", "BM2"],
      ["NV", "M3", "NV", "BM3", "BM3"],
      ["NV", "NV", "NV", "BM2", "BM2"],
      ["NV", "NV", "NV", "BM4", "BM4"]
    ],
    "Pieces": [
      { "Grid": [["N1", "N1"]] },
      { "Grid": [["N1", "N1"]] },
      { "Grid": [["N2", "N2"]] },
      { "Grid": [["N2", "N2"]] },
      { "Grid": [["N3", "N3"]] },
      { "Grid": [["N3", "N3"]] },
      { "Grid": [["N4", "N4"]] },
      { "Grid": [["N4", "N4"]] },
      {
        "Grid": [
          ["N5", "N5"],
          ["N5", "NV"]
        ]
      },
      {
        "Grid": [
          ["NV", "N3"],
          ["NV", "N3"],
          ["N3", "N3"],
          ["NV", "N3"],
          ["NV", "N3"]
        ]
      }
    ],
    "Filled_grid": [
      [2, 2, 1, 9, 9],
      [3, 3, 1, 6, 6],
      [3, 1, 1, 8, 8],
      [4, 4, 1, 7, 7],
      [5, 5, 1, 10, 10]
    ]
  },
  "26": {
    "Grid": [
      ["NV", "NV", "BNV", "BNV", "BNV", "BNV"],
      ["NV", "NV", "NV", "BNV", "BNV", "BNV"],
      ["NV", "NV", "NV", "BNV", "BNV", "BH0"],
      ["NV", "NV", "NV", "BNV", "BH0", "BH0"],
      ["NV", "NV", "NV", "NV", "BNV", "BNV"],
      ["NV", "NV", "NV", "NV", "NV", "NV"]
    ],
    "Pieces": [
      { "Grid": [["N1", "N1"]] },
      {
        "Grid": [
          ["N3", "N3"],
          ["N3", "NV"]
        ]
      },
      {
        "Grid": [
          ["N1", "NV", "NV"],
          ["NV", "N1", "N1"]
        ]
      },
      {
        "Grid": [
          ["N2", "N2", "N2"],
          ["NV", "NV", "N2"]
        ]
      },
      {
        "Grid": [
          ["N3", "NV", "NV"],
          ["N3", "N3", "N3"]
        ]
      },
      {
        "Grid": [
          ["N6", "NV"],
          ["N6", "N6"],
          ["N6", "N6"]
        ]
      },
      {
        "Grid": [
          ["N4", "N4"],
          ["NV", "N4"]
        ]
      },
      {
        "Grid": [
          ["N1", "NV"],
          ["N1", "N1"]
        ]
      },
      { "Grid": [["N6"], ["N6"], ["N6"]] },
      { "Grid": [["N3"], ["N3"], ["N3"]] }
    ],
    "Filled_grid": [
      [2, 1, 8, 7, 7, 7],
      [2, 1, 1, 8, 8, 7],
      [2, 1, 1, 9, 9, null],
      [3, 5, 5, 9, null, null],
      [3, 6, 5, 4, 10, 10],
      [3, 6, 6, 4, 4, 4]
    ]
  },
  "27": {
    "Grid": [
      ["NV", "NV", "NV", "NV", "NV"],
      ["NV", "BM6", "M4", "BM3", "NV"],
      ["NV", "M4", "M4", "NV", "M4"],
      ["NV", "BM5", "NV", "BM1", "NV"],
      ["NV", "NV", "NV", "M6", "NV"]
    ],
    "Pieces": [
      { "Grid": [["N4"]] },
      { "Grid": [["N6"]] },
      {
        "Grid": [
          ["N2", "N2"],
          ["N2", "NV"]
        ]
      },
      { "Grid": [["N5"]] },
      { "Grid": [["N1"]] },
      { "Grid": [["N3"]] },
      { "Grid": [["N2"]] },
      { "Grid": [["N3"]] },
      { "Grid": [["N2"]] },
      { "Grid": [["N4"]] },
      {
        "Grid": [
          ["N6", "N6"],
          ["NV", "N6"]
        ]
      },
      { "Grid": [["N1", "N1"]] },
      {
        "Grid": [
          ["N4", "N4"],
          ["NV", "N4"]
        ]
      },
      {
        "Grid": [
          ["N6", "NV"],
          ["N6", "N6"]
        ]
      },
      { "Grid": [["N4", "N4"]] }
    ],
    "Filled_grid": [
      [7, 7, 11, 2, 2],
      [7, 15, 5, 16, 2],
      [10, 4, 4, 3, 3],
      [9, 14, 1, 13, 3],
      [8, 8, 1, 1, 12]
    ]
  },
  "28": {
    "Grid": [
      ["BM1", "NV", "BM4", "NV"],
      ["NV", "BM5", "NV", "BM4"],
      ["BM2", "NV", "BM3", "NV"],
      ["NV", "BM6", "NV", "BM3"]
    ],
    "Pieces": [
      { "Grid": [["N3"]] },
      { "Grid": [["N6"]] },
      { "Grid": [["N3"]] },
      { "Grid": [["N1"]] },
      { "Grid": [["N5"]] },
      { "Grid": [["N6"]] },
      { "Grid": [["N1"]] },
      { "Grid": [["N5"]] },
      { "Grid": [["N2"]] },
      { "Grid": [["N3"]] },
      { "Grid": [["N2"]] },
      { "Grid": [["N4"]] },
      { "Grid": [["N4"]] },
      { "Grid": [["N4"]] },
      { "Grid": [["N5"]] },
      { "Grid": [["N1"]] }
    ],
    "Filled_grid": [
      [17, 10, 15, 11],
      [9, 18, 2, 16],
      [19, 3, 13, 1],
      [12, 20, 4, 14]
    ]
  },
  "29": {
    "Grid": [
      ["NV", "NV", "NV", "NV", "NV", "NV"],
      ["NV", "NV", "H0", "H0", "NV", "NV"],
      ["NV", "H0", "BH0", "BNV", "H0", "NV"],
      ["NV", "H0", "BNV", "BNV", "H0", "BNV"],
      ["NV", "NV", "H0", "H0", "BNV", "BH0"],
      ["NV", "NV", "NV", "BH0", "BH0", "BNV"]
    ],
    "Pieces": [
      { "Grid": [["N1"], ["N1"], ["N1"]] },
      {
        "Grid": [
          ["N2", "NV"],
          ["N2", "N2"]
        ]
      },
      { "Grid": [["N5"]] },
      {
        "Grid": [
          ["N2", "NV"],
          ["N2", "N2"],
          ["N2", "NV"]
        ]
      },
      {
        "Grid": [
          ["N4", "NV"],
          ["NV", "N4"]
        ]
      },
      { "Grid": [["N5"], ["N5"]] },
      { "Grid": [["N4"]] },
      {
        "Grid": [
          ["NV", "N4"],
          ["NV", "N4"],
          ["N4", "N4"]
        ]
      },
      {
        "Grid": [
          ["NV", "N6"],
          ["N6", "N6"],
          ["N6", "NV"]
        ]
      }
    ],
    "Filled_grid": [
      [14, 14, 14, 16, 16, 15],
      [13, 13, null, null, 15, 15],
      [13, null, null, 20, null, 15],
      [13, null, 20, 20, null, 19],
      [7, 7, null, null, 18, null],
      [17, 7, 7, null, null, 18]
    ]
  },
  "30": {
    "Grid": [
      ["BM1", "BM6", "BM6", "BM5", "BM3"],
      ["BM1", "BM6", "NV", "BM3", "BM5"],
      ["BM5", "NV", "NV", "NV", "BM3"],
      ["BM5", "BM2", "NV", "BM4", "BM3"],
      ["BM1", "BM2", "BM4", "BM4", "BM4"]
    ],
    "Pieces": [
      { "Grid": [["N1"], ["N1"]] },
      { "Grid": [["N5"], ["N5"]] },
      {
        "Grid": [
          ["NV", "N4"],
          ["N4", "N4"]
        ]
      },
      { "Grid": [["N2"], ["N2"]] },
      { "Grid": [["N1"]] },
      { "Grid": [["N4", "N4"]] },
      {
        "Grid": [
          ["NV", "N6"],
          ["N6", "NV"]
        ]
      },
      {
        "Grid": [
          ["N4", "NV"],
          ["NV", "N4"]
        ]
      },
      { "Grid": [["N3"], ["N3"]] },
      {
        "Grid": [
          ["NV", "N3"],
          ["N3", "NV"]
        ]
      },
      {
        "Grid": [
          ["N5", "NV"],
          ["NV", "N5"]
        ]
      },
      {
        "Grid": [
          ["N6", "N6"],
          ["N6", "NV"]
        ]
      }
    ],
    "Filled_grid": [
      [8, 9, 9, 11, 10],
      [8, 9, 3, 10, 11],
      [6, 3, 4, 4, 14],
      [6, 5, 4, 13, 14],
      [7, 5, 12, 12, 13]
    ]
  },
  "31": {
    "Grid": [
      ["NV", "NV", "NV", "NV", "NV"],
      ["NV", "NV", "NV", "NV", "NV"],
      ["NV", "NV", "NV", "NV", "NV"],
      ["NV", "NV", "NV", "NV", "NV"],
      ["NV", "NV", "NV", "NV", "NV"]
    ],
    "Pieces": [
      {
        "Grid": [
          ["NV", "N4", "N4"],
          ["N4", "N4", "NV"]
        ]
      },
      {
        "Grid": [
          ["N2", "N2"],
          ["N2", "N2"]
        ]
      },
      {
        "Grid": [
          ["N1", "N1"],
          ["N1", "N1"],
          ["N1", "NV"]
        ]
      },
      { "Grid": [["N3"], ["N3"], ["N3"]] },
      { "Grid": [["N5"]] },
      {
        "Grid": [
          ["N5", "N5", "N5"],
          ["NV", "NV", "N5"]
        ]
      },
      {
        "Grid": [
          ["NV", "NV", "N1"],
          ["N1", "N1", "N1"]
        ]
      }
    ],
    "Filled_grid": [
      [1, 1, 8, 8, 9],
      [1, 1, 8, 8, 9],
      [1, 10, 10, 10, 9],
      [13, 11, 11, 10, 12],
      [11, 11, 12, 12, 12]
    ]
  },
  "32": {
    "Grid": [
      ["NV", "NV", "NV", "BNV", "BNV", "BNV", "BNV"],
      ["NV", "NV", "NV", "BNV", "BNV", "BNV", "BNV"],
      ["NV", "NV", "NV", "BNV", "BNV", "BNV", "BNV"],
      ["NV", "NV", "NV", "NV", "BNV", "BNV", "BNV"],
      ["NV", "NV", "NV", "NV", "BNV", "BNV", "BNV"]
    ],
    "Pieces": [
      {
        "Grid": [
          ["NV", "N4"],
          ["NV", "N4"],
          ["N4", "N4"]
        ]
      },
      { "Grid": [["N3"]] },
      {
        "Grid": [
          ["N4", "N4", "NV"],
          ["NV", "N4", "N4"]
        ]
      },
      { "Grid": [["N3"], ["N3"], ["N3"]] },
      { "Grid": [["N5", "N5"]] },
      {
        "Grid": [
          ["NV", "N1"],
          ["N1", "N1"],
          ["N1", "N1"]
        ]
      },
      {
        "Grid": [
          ["N4", "N4"],
          ["N4", "N4"]
        ]
      },
      {
        "Grid": [
          ["NV", "N3"],
          ["N3", "N3"]
        ]
      },
      {
        "Grid": [
          ["NV", "N2"],
          ["N2", "N2"],
          ["N2", "NV"]
        ]
      },
      { "Grid": [["N6"]] },
      {
        "Grid": [
          ["N2", "NV", "NV"],
          ["N2", "N2", "N2"]
        ]
      }
    ],
    "Filled_grid": [
      [93, 92, 91, 102, 103, 103, 101],
      [92, 92, 91, 102, 102, 102, 101],
      [92, 90, 91, 98, 98, 101, 101],
      [90, 90, 89, 89, 98, 98, 100],
      [90, 90, 89, 89, 104, 100, 100]
    ]
  },
  "33": {
    "Grid": [
      ["H0", "NV", "NV", "NV", "NV", "NV"],
      ["NV", "NV", "NV", "NV", "NV", "NV"],
      ["NV", "NV", "NV", "NV", "NV", "NV"],
      ["NV", "NV", "NV", "NV", "NV", "NV"],
      ["NV", "NV", "NV", "NV", "NV", "NV"]
    ],
    "Pieces": [
      {
        "Grid": [
          ["N6", "N6"],
          ["N6", "NV"],
          ["N6", "NV"]
        ]
      },
      {
        "Grid": [
          ["N1", "N1"],
          ["N1", "NV"],
          ["N1", "NV"],
          ["N1", "NV"]
        ]
      },
      {
        "Grid": [
          ["N5", "N5"],
          ["N5", "N5"],
          ["N5", "NV"]
        ]
      },
      {
        "Grid": [
          ["N3", "NV"],
          ["N3", "N3"],
          ["NV", "N3"]
        ]
      },
      {
        "Grid": [
          ["N2", "N2"],
          ["N2", "NV"],
          ["N2", "NV"],
          ["N2", "NV"]
        ]
      },
      {
        "Grid": [
          ["NV", "NV", "N1"],
          ["N1", "N1", "NV"]
        ]
      },
      { "Grid": [["N3", "N3", "N3"]] }
    ],
    "Filled_grid": [
      [null, 28, 28, 28, 26, 26],
      [29, 29, 31, 28, 26, 27],
      [29, 29, 31, 31, 26, 27],
      [29, 30, 30, 31, 26, 27],
      [30, 32, 32, 32, 27, 27]
    ]
  },
  "34": {
    "Grid": [
      ["NV", "NV", "NV", "BM5", "BM5", "BM3"],
      ["NV", "NV", "NV", "BM5", "BM3", "BM3"],
      ["NV", "NV", "NV", "BM2", "BM2", "BM1"],
      ["NV", "NV", "NV", "BM2", "BM2", "BM1"],
      ["NV", "NV", "NV", "BM2", "BM6", "BM6"]
    ],
    "Pieces": [
      {
        "Grid": [
          ["N2", "N2"],
          ["NV", "N2"]
        ]
      },
      { "Grid": [["N6"], ["N6"]] },
      { "Grid": [["N2"], ["N2"]] },
      { "Grid": [["N1"], ["N1"]] },
      { "Grid": [["N6", "N6"]] },
      {
        "Grid": [
          ["NV", "N5"],
          ["N5", "N5"]
        ]
      },
      {
        "Grid": [
          ["N5", "N5"],
          ["N5", "NV"]
        ]
      },
      {
        "Grid": [
          ["N3", "NV"],
          ["N3", "N3"]
        ]
      },
      {
        "Grid": [
          ["N2", "N2"],
          ["N2", "NV"]
        ]
      },
      { "Grid": [["N2", "N2"]] },
      {
        "Grid": [
          ["NV", "N3"],
          ["N3", "N3"]
        ]
      },
      { "Grid": [["N1", "N1"]] }
    ],
    "Filled_grid": [
      [32, 32, 31, 40, 40, 41],
      [33, 31, 31, 40, 41, 41],
      [33, 34, 34, 37, 37, 39],
      [35, 29, 34, 36, 36, 39],
      [35, 29, 29, 36, 38, 38]
    ]
  },
  "35": {
    "Grid": [
      ["M2", "M2", "M2", "BM2", "BM2", "BM2"],
      ["M2", "M2", "M2", "BM2", "BM2", "BM2"],
      ["M2", "M2", "M2", "BM2", "BM2", "BM2"],
      ["M4", "M4", "M4", "BM4", "BM4", "BM4"],
      ["M4", "M4", "M4", "BM4", "BM4", "BM4"],
      ["M4", "M4", "M4", "BM4", "BM4", "BH0"]
    ],
    "Pieces": [
      { "Grid": [["N2"], ["N2"], ["N4"]] },
      {
        "Grid": [
          ["N2", "N2", "N2"],
          ["NV", "NV", "N2"]
        ]
      },
      {
        "Grid": [
          ["N4", "NV", "N4"],
          ["N4", "N4", "NV"]
        ]
      },
      {
        "Grid": [
          ["NV", "N2"],
          ["N4", "NV"]
        ]
      },
      {
        "Grid": [
          ["NV", "N2"],
          ["N2", "NV"]
        ]
      },
      { "Grid": [["N2"], ["NV"], ["N2"]] },
      { "Grid": [["N2"]] },
      {
        "Grid": [
          ["NV", "N4"],
          ["N4", "N4"]
        ]
      },
      { "Grid": [["N2"], ["N4"], ["N4"]] },
      {
        "Grid": [
          ["N2", "NV"],
          ["NV", "NV"],
          ["NV", "N4"]
        ]
      },
      {
        "Grid": [
          ["NV", "N2", "N2"],
          ["N2", "N2", "NV"]
        ]
      },
      { "Grid": [["N4"], ["N4"], ["N4"]] },
      { "Grid": [["N4", "N4"]] }
    ],
    "Filled_grid": [
      [3, 2, 2, 13, 13, 13],
      [2, 2, 5, 18, 19, 13],
      [3, 5, 4, 18, 17, 20],
      [9, 4, 8, 18, 17, 19],
      [9, 8, 8, 14, 17, 14],
      [9, 10, 10, 14, 14, null]
    ]
  },
  "36": {
    "Grid": [
      ["H0", "M1", "M4", "M1", "M4", "H0"],
      ["M1", "M1", "M1", "M4", "M4", "M1"],
      ["M4", "M1", "H0", "M1", "H0", "H0"],
      ["M4", "M4", "M1", "M4", "M1", "M4"],
      ["M4", "M1", "M4", "M1", "M4", "H0"]
    ],
    "Pieces": [
      {
        "Grid": [
          ["NV", "N1"],
          ["N4", "N4"],
          ["N1", "NV"]
        ]
      },
      {
        "Grid": [
          ["N1", "N1", "NV"],
          ["NV", "N1", "N4"]
        ]
      },
      {
        "Grid": [
          ["N4", "NV"],
          ["N1", "N4"],
          ["NV", "N1"]
        ]
      },
      {
        "Grid": [
          ["NV", "N1", "N4"],
          ["N1", "N4", "NV"]
        ]
      },
      {
        "Grid": [
          ["NV", "N1"],
          ["N4", "N4"],
          ["N4", "NV"]
        ]
      },
      {
        "Grid": [
          ["NV", "N4", "N1"],
          ["N4", "N1", "NV"]
        ]
      }
    ],
    "Filled_grid": [
      [null, 4, 5, 3, 3, null],
      [4, 4, 5, 5, 3, 3],
      [4, 1, null, 5, null, null],
      [1, 1, 2, 2, 6, 6],
      [1, 2, 2, 6, 6, null]
    ]
  },
  "37": {
    "Grid": [
      ["NV", "NV", "NV", "TV"],
      ["NV", "NV", "NV", "NV"],
      ["NV", "NV", "NV", "NV"],
      ["TV", "TV", "NV", "NV"]
    ],
    "Message": 39,
    "Pieces": [
      {
        "Grid": [
          ["NV", "N6"],
          ["N6", "N6"]
        ]
      },
      {
        "Grid": [
          ["N1", "N1"],
          ["N1", "NV"],
          ["N1", "NV"]
        ]
      },
      {
        "Grid": [
          ["N2", "N2"],
          ["NV", "N2"]
        ]
      },
      {
        "Grid": [
          ["N3", "NV"],
          ["N3", "N3"]
        ]
      },
      { "Grid": [["N5", "N5"]] },
      { "Grid": [["N1"], ["N1"]] },
      { "Grid": [["N3", "N3"]] }
    ],
    "Filled_grid": [
      [7, 7, 3, 4],
      [6, 6, 3, 4],
      [1, 6, 3, 5],
      [2, 2, 5, 5]
    ]
  },
  "38": {
    "Grid": [
      ["NV", "TV", "NV", "NV", "NV"],
      ["NV", "TV", "NV", "NV", "NV"],
      ["NV", "TV", "TV", "TV", "NV"],
      ["NV", "NV", "NV", "TV", "NV"],
      ["NV", "NV", "NV", "TV", "NV"]
    ],
    "Pieces": [
      {
        "Grid": [
          ["N4", "N4", "N4", "N4"],
          ["N4", "NV", "NV", "NV"]
        ]
      },
      {
        "Grid": [
          ["N6", "N6", "N6"],
          ["N6", "NV", "NV"]
        ]
      },
      {
        "Grid": [
          ["NV", "N3"],
          ["N3", "N3"],
          ["N3", "N3"]
        ]
      },
      { "Grid": [["N4"], ["N4"]] },
      {
        "Grid": [
          ["NV", "N6", "N6"],
          ["N6", "N6", "NV"]
        ]
      },
      {
        "Grid": [
          ["N4", "N4", "NV"],
          ["N4", "N4", "N4"]
        ]
      },
      {
        "Grid": [
          ["NV", "N3", "N3"],
          ["N3", "N3", "N3"]
        ]
      },
      { "Grid": [["N6", "N6"]] }
    ],
    "Filled_grid": [
      [6, 6, 5, 5, 5],
      [6, 6, 6, 9, 9],
      [10, 10, 9, 9, 1],
      [7, 8, 2, 2, 1],
      [7, 2, 2, 2, 1]
    ]
  },
  "39": {
    "Grid": [
      ["TV", "TV", "TV"],
      ["TV", "TV", "TV"],
      ["TV", "TV", "TV"]
    ],
    "Pieces": [
      {
        "Grid": [
          ["NV", "N1"],
          ["NV", "N4"],
          ["N2", "N2"]
        ]
      },
      { "Grid": [["N1"], ["N4"]] },
      {
        "Grid": [
          ["N4", "N4"],
          ["NV", "N2"]
        ]
      },
      { "Grid": [["N1"], ["N4"], ["N4"]] },
      { "Grid": [["N1", "N1"]] },
      {
        "Grid": [
          ["N1", "NV"],
          ["N4", "NV"],
          ["N4", "N2"]
        ]
      }
    ],
    "Filled_grid": [
      [3, 6, 6],
      [3, 5, 4],
      [3, 2, 4]
    ]
  },
  "40": {
    "Grid": [
      ["NV", "NV", "NV", "NV", "NV"],
      ["NV", "TV", "NV", "TV", "NV"],
      ["NV", "TV", "NV", "TV", "NV"],
      ["NV", "TV", "NV", "TV", "NV"],
      ["NV", "NV", "NV", "NV", "NV"]
    ],
    "Pieces": [
      {
        "Grid": [
          ["NV", "N3"],
          ["N3", "N3"],
          ["NV", "N3"]
        ]
      },
      {
        "Grid": [
          ["NV", "N4"],
          ["NV", "N4"],
          ["N4", "N4"]
        ]
      },
      {
        "Grid": [
          ["N1", "N1", "N1"],
          ["N1", "N1", "NV"]
        ]
      },
      {
        "Grid": [
          ["NV", "N6"],
          ["N6", "N6"],
          ["N6", "N6"]
        ]
      },
      {
        "Grid": [
          ["N1", "N1"],
          ["NV", "N1"],
          ["NV", "N1"]
        ]
      },
      { "Grid": [["N3"], ["N3"]] },
      {
        "Grid": [
          ["N4", "NV"],
          ["N4", "N4"],
          ["NV", "N4"]
        ]
      },
      {
        "Grid": [
          ["N6", "N6"],
          ["NV", "N6"]
        ]
      }
    ],
    "Filled_grid": [
      [5, 5, 5, 10, 9],
      [5, 6, 6, 10, 9],
      [4, 4, 6, 8, 9],
      [3, 4, 6, 8, 7],
      [3, 3, 8, 8, 7]
    ]
  },
  "41": {
    "Grid": [
      ["TV", "TV", "TV", "TV"],
      ["TV", "TV", "TV", "TV"],
      ["TV", "TV", "TV", "H0"],
      ["TV", "TV", "H0", "H0"]
    ],
    "Pieces": [
      {
        "Grid": [
          ["N1", "N1", "NV", "N3"],
          ["NV", "N4", "N6", "N6"]
        ]
      },
      {
        "Grid": [
          ["N3", "NV"],
          ["N5", "N5"],
          ["N4", "N1"]
        ]
      },
      {
        "Grid": [
          ["NV", "N5", "N6"],
          ["N4", "N1", "NV"]
        ]
      },
      { "Grid": [["N4", "N3"]] },
      {
        "Grid": [
          ["N1", "N1"],
          ["N3", "NV"],
          ["N5", "NV"]
        ]
      },
      {
        "Grid": [
          ["NV", "N4", "NV"],
          ["N4", "N6", "N6"],
          ["NV", "N6", "NV"]
        ]
      }
    ],
    "Filled_grid": [
      [6, 6, 3, 3],
      [6, 2, 2, 2],
      [6, 5, 5, null],
      [5, 5, null, null]
    ]
  },
  "42": {
    "Grid": [
      ["NV", "NV", "NV", "NV", "NV"],
      ["NV", "TV", "TV", "NV", "NV"],
      ["NV", "TV", "NV", "NV", "NV"],
      ["NV", "NV", "NV", "NV", "TV"],
      ["NV", "NV", "NV", "TV", "TV"]
    ],
    "Pieces": [
      {
        "Grid": [
          ["NV", "N6"],
          ["N6", "N6"],
          ["N6", "N6"]
        ]
      },
      {
        "Grid": [
          ["N3", "NV"],
          ["N3", "N3"]
        ]
      },
      {
        "Grid": [
          ["N1", "N1"],
          ["N1", "N1"],
          ["N1", "NV"]
        ]
      },
      {
        "Grid": [
          ["NV", "N3"],
          ["N3", "N3"]
        ]
      },
      {
        "Grid": [
          ["N2", "NV"],
          ["N2", "NV"],
          ["N2", "N2"]
        ]
      },
      {
        "Grid": [
          ["NV", "NV", "N6"],
          ["N6", "N6", "N6"]
        ]
      },
      {
        "Grid": [
          ["NV", "N2"],
          ["N2", "N2"],
          ["N2", "NV"]
        ]
      },
      {
        "Grid": [
          ["N2", "NV"],
          ["N2", "N2"]
        ]
      }
    ],
    "Filled_grid": [
      [5, 6, 4, 3, 3],
      [5, 6, 6, 3, 3],
      [5, 5, 7, 3, 2],
      [8, 7, 7, 2, 2],
      [8, 8, 1, 2, 2]
    ]
  },
  "43": {
    "Grid": [
      ["NV", "NV", "NV", "NV", "BNV", "BNV"],
      ["NV", "H0", "NV", "NV", "BH0", "BNV"],
      ["NV", "H0", "NV", "NV", "BH0", "BNV"],
      ["NV", "H0", "NV", "BNV", "BH0", "BNV"],
      ["NV", "H0", "BNV", "BNV", "BH0", "BNV"],
      ["NV", "NV", "BNV", "BNV", "BNV", "BNV"]
    ],
    "Pieces": [
      {
        "Grid": [
          ["NV", "N1"],
          ["N1", "N1"]
        ]
      },
      {
        "Grid": [
          ["NV", "N1"],
          ["N1", "N1"],
          ["N1", "NV"]
        ]
      },
      {
        "Grid": [
          ["NV", "N5"],
          ["N5", "N5"]
        ]
      },
      {
        "Grid": [
          ["N2", "NV", "NV"],
          ["N2", "NV", "NV"],
          ["N2", "N2", "N2"]
        ]
      },
      { "Grid": [["N5"]] },
      {
        "Grid": [
          ["N3", "NV"],
          ["N3", "NV"],
          ["N3", "N3"]
        ]
      },
      { "Grid": [["N4", "N4", "N4"]] },
      {
        "Grid": [
          ["N6", "N6", "N6", "NV"],
          ["NV", "NV", "N6", "N6"]
        ]
      }
    ],
    "Filled_grid": [
      [2, 4, 4, 3, 7, 7],
      [2, null, 4, 3, null, 7],
      [2, null, 3, 3, null, 8],
      [1, null, 3, 6, null, 5],
      [1, null, 6, 6, null, 5],
      [1, 1, 6, 5, 5, 5]
    ]
  },
  "44": {
    "Grid": [
      ["NV", "NV", "NV", "NV", "TV"],
      ["NV", "NV", "TV", "NV", "NV"],
      ["TV", "NV", "NV", "NV", "NV"],
      ["NV", "NV", "NV", "TV", "NV"],
      ["NV", "TV", "NV", "NV", "NV"]
    ],
    "Pieces": [
      {
        "Grid": [
          ["NV", "N3"],
          ["N3", "N3"],
          ["NV", "N3"]
        ]
      },
      {
        "Grid": [
          ["N3", "NV"],
          ["N3", "NV"],
          ["N3", "N3"]
        ]
      },
      {
        "Grid": [
          ["NV", "NV", "N3"],
          ["N3", "N3", "N3"]
        ]
      },
      {
        "Grid": [
          ["N3", "N3", "NV"],
          ["NV", "N3", "N3"]
        ]
      },
      {
        "Grid": [
          ["NV", "N4"],
          ["N4", "N4"],
          ["N4", "NV"]
        ]
      },
      {
        "Grid": [
          ["N4", "N4"],
          ["NV", "N4"]
        ]
      },
      {
        "Grid": [
          ["N4", "N4", "N4"],
          ["N4", "NV", "NV"]
        ]
      },
      {
        "Grid": [
          ["N4", "N4"],
          ["N4", "NV"]
        ]
      }
    ],
    "Filled_grid": [
      [9, 9, 7, 7, 7],
      [9, 8, 8, 6, 6],
      [5, 5, 8, 6, 4],
      [2, 5, 5, 4, 4],
      [2, 2, 1, 1, 4]
    ]
  },
  "45": {
    "Grid": [
      ["NV", "TV", "NV", "TV", "NV"],
      ["TV", "NV", "NV", "NV", "TV"],
      ["NV", "NV", "TV", "NV", "NV"],
      ["NV", "TV", "NV", "TV", "NV"],
      ["NV", "NV", "TV", "NV", "NV"]
    ],
    "Pieces": [
      {
        "Grid": [
          ["NV", "N1", "NV"],
          ["N1", "N1", "N1"],
          ["NV", "N1", "NV"]
        ]
      },
      {
        "Grid": [
          ["N1", "N1"],
          ["N1", "NV"]
        ]
      },
      {
        "Grid": [
          ["NV", "N1"],
          ["N1", "N1"],
          ["N1", "NV"]
        ]
      },
      {
        "Grid": [
          ["N1", "NV"],
          ["N1", "N1"]
        ]
      },
      {
        "Grid": [
          ["NV", "NV", "N5"],
          ["N5", "N5", "N5"]
        ]
      },
      {
        "Grid": [
          ["N5", "NV"],
          ["NV", "N5"]
        ]
      },
      {
        "Grid": [
          ["N5", "N5", "N5"],
          ["N5", "NV", "N5"]
        ]
      },
      {
        "Grid": [
          ["NV", "N5"],
          ["N5", "N5"],
          ["N5", "NV"]
        ]
      },
      {
        "Grid": [
          ["N5", "NV"],
          ["N5", "N5"]
        ]
      }
    ],
    "Filled_grid": [
      [17, 17, 18, 19, 18],
      [17, 16, 18, 20, 19],
      [16, 22, 21, 20, 20],
      [22, 23, 21, 21, 24],
      [22, 23, 24, 24, 24]
    ]
  },
  "46": {
    "Grid": [
      ["BTV", "BNV", "BNV", "BTV", "BNV"],
      ["BNV", "BTV", "BNV", "NV", "NV"],
      ["BNV", "BTV", "BNV", "NV", "NV"],
      ["BNV", "BNV", "BTV", "NV", "NV"],
      ["BTV", "BNV", "BNV", "NV", "NV"]
    ],
    "Pieces": [
      {
        "Grid": [
          ["NV", "N1", "N1"],
          ["N4", "N4", "NV"]
        ]
      },
      { "Grid": [["N4"], ["N4"], ["N4"]] },
      {
        "Grid": [
          ["N6", "N6"],
          ["NV", "N6"],
          ["NV", "N6"]
        ]
      },
      { "Grid": [["N1"], ["N1"]] },
      {
        "Grid": [
          ["N6", "NV", "NV"],
          ["N6", "N6", "NV"],
          ["NV", "N6", "N6"]
        ]
      },
      { "Grid": [["N2"], ["N2"], ["N2"]] },
      {
        "Grid": [
          ["N3", "N3"],
          ["NV", "N3"],
          ["NV", "N3"]
        ]
      },
      { "Grid": [["N5"]] },
      {
        "Grid": [
          ["N5", "N5", "N5"],
          ["N5", "NV", "NV"]
        ]
      },
      { "Grid": [["N4"]] }
    ],
    "Filled_grid": [
      [9, 9, 10, 11, 10],
      [8, 9, 10, 5, 5],
      [12, 9, 8, 6, 5],
      [12, 13, 14, 6, 5],
      [13, 13, 14, 6, 7]
    ]
  },
  "47": {
    "Grid": [
      ["NV", "TV", "NV", "TV", "NV"],
      ["TV", "TV", "NV", "TV", "TV"],
      ["NV", "NV", "NV", "NV", "NV"],
      ["TV", "TV", "NV", "TV", "TV"],
      ["NV", "TV", "NV", "TV", "NV"]
    ],
    "Pieces": [
      {
        "Grid": [
          ["N6", "N6", "N6"],
          ["N6", "NV", "NV"]
        ]
      },
      {
        "Grid": [
          ["NV", "N4"],
          ["N3", "N3"]
        ]
      },
      {
        "Grid": [
          ["NV", "NV", "N1"],
          ["N6", "N1", "N1"]
        ]
      },
      {
        "Grid": [
          ["NV", "N3", "N3"],
          ["NV", "N3", "NV"],
          ["N3", "N3", "NV"]
        ]
      },
      {
        "Grid": [
          ["NV", "N3", "NV"],
          ["N3", "N3", "N3"]
        ]
      },
      { "Grid": [["N1"], ["N1"], ["N4"], ["N4"]] },
      { "Grid": [["N1"], ["N4"]] },
      {
        "Grid": [
          ["NV", "N6"],
          ["N6", "N6"]
        ]
      },
      {
        "Grid": [
          ["N3", "NV"],
          ["N3", "N3"]
        ]
      },
      { "Grid": [["N3"]] },
      {
        "Grid": [
          ["NV", "N4"],
          ["NV", "N4"],
          ["N4", "N4"]
        ]
      }
    ],
    "Filled_grid": [
      [1, 2, 1, 4, 5],
      [2, 3, 3, 4, 6],
      [10, 8, 8, 4, 6],
      [11, 10, 9, 6, 7],
      [8, 9, 9, 9, 7]
    ]
  },
  "48": {
    "Grid": [
      ["TV", "TV", "TV", "TV", "TV", "TV"],
      ["TV", "M1", "M1", "M6", "M6", "TV"],
      ["TV", "M1", "M1", "M4", "M6", "TV"],
      ["TV", "M2", "M1", "M4", "M4", "TV"],
      ["TV", "M2", "M2", "M2", "M4", "TV"],
      ["TV", "TV", "TV", "TV", "TV", "TV"]
    ],
    "Pieces": [
      {
        "Grid": [
          ["NV", "NV", "N4"],
          ["NV", "NV", "N4"],
          ["N4", "N4", "N4"]
        ]
      },
      {
        "Grid": [
          ["N1", "N1"],
          ["NV", "N1"],
          ["NV", "N1"],
          ["NV", "N1"]
        ]
      },
      { "Grid": [["N4"], ["N4"], ["N4"]] },
      { "Grid": [["N2"], ["N2"], ["N2"]] },
      { "Grid": [["N2"], ["N5"], ["N2"]] },
      { "Grid": [["N2"]] },
      {
        "Grid": [
          ["NV", "N1", "N1"],
          ["N1", "N1", "N1"]
        ]
      },
      {
        "Grid": [
          ["N6", "NV"],
          ["N6", "N6"]
        ]
      },
      { "Grid": [["N4", "N4", "N6", "N6"]] },
      { "Grid": [["N1"], ["N1"], ["N1"]] },
      {
        "Grid": [
          ["NV", "NV", "N6"],
          ["N6", "N6", "N6"]
        ]
      },
      { "Grid": [["N6"], ["N6"]] },
      {
        "Grid": [
          ["N2", "N2", "N2"],
          ["NV", "NV", "N2"]
        ]
      },
      {
        "Grid": [
          ["NV", "N4", "N4"],
          ["N4", "N4", "NV"]
        ]
      },
      {
        "Grid": [
          ["NV", "NV", "N2"],
          ["NV", "NV", "N2"],
          ["N5", "N2", "N2"]
        ]
      },
      { "Grid": [["N1", "N1"]] }
    ],
    "Filled_grid": [
      [14, 15, 15, 16, 12, 12],
      [14, 1, 1, 3, 3, 11],
      [14, 1, 1, 2, 3, 11],
      [10, 4, 1, 2, 2, 11],
      [10, 4, 4, 4, 2, 8],
      [10, 9, 9, 7, 7, 8]
    ]
  },
  "49": {
    "Grid": [
      ["TV", "NV", "TV", "NV", "TV"],
      ["TV", "NV", "TV", "NV", "TV"],
      ["TV", "NV", "TV", "NV", "TV"],
      ["TV", "NV", "TV", "NV", "TV"],
      ["TV", "NV", "TV", "NV", "TV"]
    ],
    "Pieces": [
      {
        "Grid": [
          ["N6", "N6", "NV"],
          ["NV", "N5", "N5"]
        ]
      },
      {
        "Grid": [
          ["N2", "N1", "NV"],
          ["N2", "N1", "NV"],
          ["N2", "N1", "N3"]
        ]
      },
      {
        "Grid": [
          ["N6", "N6", "N6"],
          ["NV", "N1", "NV"]
        ]
      },
      { "Grid": [["N6", "N6", "N6", "N6", "N6"]] },
      {
        "Grid": [
          ["NV", "N1", "N4"],
          ["N6", "N1", "N4"]
        ]
      },
      { "Grid": [["N5", "N5", "N3", "N4", "N4"]] },
      {
        "Grid": [
          ["N3", "N1", "NV"],
          ["N3", "N1", "N5"]
        ]
      },
      { "Grid": [["N2", "N2", "N2", "N3", "N3"]] }
    ],
    "Filled_grid": [
      [13, 13, 12, 12, 12],
      [15, 13, 13, 12, 12],
      [15, 15, 14, 14, 14],
      [15, 10, 10, 14, 14],
      [10, 10, 10, 14, 14]
    ]
  },
  "50": {
    "# Level 42": "",
    "Grid": [
      ["NV", "NV", "NV", "NV", "NV"],
      ["NV", "TV", "NV", "TV", "NV"],
      ["NV", "NV", "NV", "NV", "NV"],
      ["NV", "NV", "NV", "TV", "NV"],
      ["NV", "TV", "TV", "NV", "NV"]
    ],
    "Pieces": [
      { "Grid": [["N3", "N2"]] },
      { "Grid": [["N1", "N1", "N2"]] },
      {
        "Grid": [
          ["NV", "N2", "NV"],
          ["N3", "N1", "N6"]
        ]
      },
      {
        "Grid": [
          ["NV", "N3", "N3"],
          ["N6", "N6", "NV"]
        ]
      },
      {
        "Grid": [
          ["N4", "N1"],
          ["NV", "N1"],
          ["NV", "N2"]
        ]
      },
      {
        "Grid": [
          ["N3", "N3", "N2"],
          ["NV", "NV", "N2"]
        ]
      },
      { "Grid": [["N1"], ["N6"], ["N1"], ["N6"]] },
      {
        "Grid": [
          ["N6", "N3"],
          ["NV", "N4"],
          ["NV", "N5"],
          ["NV", "N1"]
        ]
      }
    ],
    "Filled_grid": [
      [9, 8, 5, 5, 5],
      [9, 8, 5, 4, 2],
      [9, 7, 7, 4, 2],
      [6, 7, 3, 4, 2],
      [6, 6, 6, 4, 2]
    ]
  },
  "001-no": {
    "Grid": [
      ["NV", "NV", "NV", "NV", "NV", "NV"],
      ["NV", "NV", "NV", "NV", "NV", "NV"],
      ["NV", "NV", "NV", "NV", "NV", "NV"],
      ["NV", "NV", "NV", "NV", "NV", "NV"],
      ["NV", "NV", "NV", "NV", "NV", "NV"]
    ],
    "Pieces": [
      {
        "Grid": [
          ["NV", "N1", "N1"],
          ["NV", "N1", "NV"],
          ["N1", "N1", "NV"]
        ]
      },
      {
        "Grid": [
          ["N4", "NV"],
          ["N4", "N4"],
          ["N4", "NV"]
        ]
      },
      {
        "Grid": [
          ["N2", "NV"],
          ["N2", "N2"],
          ["NV", "N2"]
        ]
      },
      {
        "Grid": [
          ["N4", "N4", "N4"],
          ["NV", "N4", "NV"]
        ]
      },
      {
        "Grid": [
          ["NV", "N2", "N2"],
          ["N2", "N2", "N2"]
        ]
      },
      {
        "Grid": [
          ["NV", "N6"],
          ["NV", "N6"],
          ["N6", "N6"]
        ]
      },
      {
        "Grid": [
          ["NV", "N4"],
          ["N4", "N4"],
          ["N4", "NV"]
        ]
      }
    ]
  },
  "002-ro-bd": {
    "Grid": [
      ["NV", "NV", "NV", "NV", "NV"],
      ["NV", "NV", "NV", "NV", "NV"],
      ["NV", "NV", "NV", "NV", "NV"],
      ["H0", "NV", "NV", "NV", "NV"],
      ["H0", "H0", "NV", "NV", "NV"]
    ],
    "Pieces": [
      {
        "Grid": [
          ["NV", "N3", "NV"],
          ["N3", "N3", "N3"],
          ["N3", "NV", "NV"]
        ]
      },
      { "Grid": [["N1"], ["N1"]] },
      {
        "Grid": [
          ["N3", "NV", "NV"],
          ["NV", "NV", "N3"]
        ]
      },
      { "Grid": [["N2"], ["N2"], ["N2"]] },
      {
        "Grid": [
          ["N2", "N2", "N2"],
          ["NV", "NV", "N2"]
        ]
      },
      {
        "Grid": [
          ["N4", "NV", "N4"],
          ["N4", "N4", "N4"]
        ]
      },
      { "Grid": [["N5"]] }
    ]
  },
  "003-no": {
    "Grid": [
      ["NV", "NV", "BNV", "BNV", "NV", "NV"],
      ["NV", "NV", "NV", "BNV", "BNV", "NV"],
      ["NV", "NV", "NV", "NV", "BNV", "NV"],
      ["NV", "NV", "NV", "NV", "BNV", "BNV"],
      ["NV", "NV", "NV", "NV", "NV", "NV"],
      ["NV", "NV", "NV", "NV", "NV", "NV"]
    ],
    "Pieces": [
      {
        "Grid": [
          ["NV", "N5"],
          ["NV", "N1"],
          ["N2", "N6"]
        ]
      },
      {
        "Grid": [
          ["N2", "N5"],
          ["N5", "N2"]
        ]
      },
      {
        "Grid": [
          ["NV", "N5"],
          ["N3", "N1"],
          ["N2", "NV"]
        ]
      },
      { "Grid": [["N2"], ["N4"]] },
      {
        "Grid": [
          ["NV", "N1", "N1"],
          ["N2", "N2", "N6"]
        ]
      },
      {
        "Grid": [
          ["N2", "N4"],
          ["N1", "NV"],
          ["N4", "NV"]
        ]
      },
      {
        "Grid": [
          ["N6", "NV"],
          ["N3", "N1"],
          ["N2", "NV"]
        ]
      },
      {
        "Grid": [
          ["N4", "N1", "NV"],
          ["NV", "N1", "N6"]
        ]
      },
      { "Grid": [["N2", "N1"]] },
      {
        "Grid": [
          ["N6", "NV"],
          ["N2", "N5"]
        ]
      }
    ]
  },
  "004-no": {
    "Grid": [
      ["NV", "NV", "NV", "NV", "NV", "NV"],
      ["NV", "NV", "NV", "NV", "NV", "NV"],
      ["NV", "NV", "NV", "NV", "NV", "NV"],
      ["NV", "NV", "NV", "NV", "NV", "NV"],
      ["NV", "NV", "NV", "NV", "NV", "NV"],
      ["NV", "NV", "NV", "NV", "NV", "NV"]
    ],
    "Pieces": [
      {
        "Grid": [
          ["NV", "N5"],
          ["NV", "N5"],
          ["N5", "N5"]
        ]
      },
      {
        "Grid": [
          ["N2", "N2"],
          ["N2", "N2"]
        ]
      },
      {
        "Grid": [
          ["N3", "NV"],
          ["N3", "N3"],
          ["NV", "N3"]
        ]
      },
      {
        "Grid": [
          ["NV", "N1", "N1"],
          ["N1", "N1", "N1"]
        ]
      },
      {
        "Grid": [
          ["N2", "N2"],
          ["N2", "NV"],
          ["N2", "NV"]
        ]
      },
      {
        "Grid": [
          ["N6", "NV"],
          ["N6", "N6"],
          ["N6", "NV"]
        ]
      },
      {
        "Grid": [
          ["N4", "N4", "NV"],
          ["NV", "N4", "N4"]
        ]
      },
      {
        "Grid": [
          ["N2", "N2"],
          ["NV", "N2"],
          ["NV", "N2"]
        ]
      },
      {
        "Grid": [
          ["N6", "NV"],
          ["N6", "N6"]
        ]
      }
    ]
  },
  "005-no": {
    "Grid": [
      ["NV", "NV", "NV", "NV", "NV", "NV"],
      ["NV", "NV", "NV", "NV", "NV", "NV"],
      ["NV", "NV", "NV", "NV", "NV", "NV"],
      ["NV", "NV", "NV", "NV", "NV", "NV"],
      ["NV", "NV", "NV", "NV", "NV", "NV"],
      ["NV", "NV", "NV", "NV", "NV", "NV"]
    ],
    "Pieces": [
      {
        "Grid": [
          ["NV", "N2"],
          ["N2", "N2"],
          ["N2", "NV"]
        ]
      },
      {
        "Grid": [
          ["NV", "NV", "N6"],
          ["N6", "N6", "N6"]
        ]
      },
      {
        "Grid": [
          ["N6", "N6"],
          ["NV", "N6"],
          ["NV", "N6"],
          ["NV", "N6"]
        ]
      },
      { "Grid": [["N3"], ["N3"], ["N3"]] },
      {
        "Grid": [
          ["NV", "N1", "N1"],
          ["N1", "N1", "N1"]
        ]
      },
      { "Grid": [["N4", "N4", "N4"]] },
      {
        "Grid": [
          ["N5", "N5", "NV"],
          ["NV", "N5", "NV"],
          ["NV", "N5", "N5"]
        ]
      },
      { "Grid": [["N5", "N5", "N5", "N5"]] },
      {
        "Grid": [
          ["N1", "N1"],
          ["N1", "NV"]
        ]
      }
    ]
  },
  "006-no": {
    "Grid": [
      ["NV", "NV", "NV", "NV", "NV", "NV"],
      ["NV", "NV", "NV", "NV", "NV", "NV"],
      ["NV", "NV", "NV", "NV", "NV", "NV"],
      ["NV", "NV", "NV", "NV", "NV", "NV"],
      ["NV", "NV", "NV", "NV", "NV", "NV"],
      ["NV", "NV", "NV", "NV", "NV", "NV"]
    ],
    "Pieces": [
      {
        "Grid": [
          ["N3", "N3", "NV"],
          ["N3", "N3", "N3"]
        ]
      },
      { "Grid": [["N1"]] },
      {
        "Grid": [
          ["NV", "N6"],
          ["NV", "N6"],
          ["N6", "N6"],
          ["NV", "N6"]
        ]
      },
      {
        "Grid": [
          ["N5", "NV"],
          ["N5", "N5"],
          ["N5", "NV"]
        ]
      },
      {
        "Grid": [
          ["N2", "N2", "N2"],
          ["NV", "NV", "N2"]
        ]
      },
      {
        "Grid": [
          ["N5", "N5", "N5"],
          ["NV", "NV", "N5"]
        ]
      },
      { "Grid": [["N2"], ["N2"], ["N2"], ["N2"]] },
      {
        "Grid": [
          ["N5", "N5"],
          ["N5", "N5"],
          ["N5", "NV"]
        ]
      },
      {
        "Grid": [
          ["NV", "N4", "N4"],
          ["N4", "N4", "NV"]
        ]
      }
    ]
  },
  "007-no": {
    "Grid": [
      ["NV", "NV", "NV", "NV", "NV", "NV"],
      ["NV", "NV", "NV", "NV", "NV", "NV"],
      ["NV", "NV", "NV", "NV", "NV", "NV"],
      ["NV", "NV", "NV", "NV", "NV", "NV"],
      ["NV", "NV", "NV", "NV", "NV", "NV"],
      ["NV", "NV", "NV", "NV", "NV", "NV"]
    ],
    "Pieces": [
      { "Grid": [["N6", "N6"]] },
      {
        "Grid": [
          ["NV", "NV", "N1"],
          ["NV", "N1", "N1"],
          ["N1", "N1", "N1"]
        ]
      },
      {
        "Grid": [
          ["N5", "N5"],
          ["NV", "N5"],
          ["NV", "N5"],
          ["NV", "N5"]
        ]
      },
      {
        "Grid": [
          ["N4", "N4", "N4"],
          ["N4", "N4", "N4"],
          ["N4", "NV", "NV"]
        ]
      },
      {
        "Grid": [
          ["N5", "NV"],
          ["N5", "N5"],
          ["N5", "NV"]
        ]
      },
      {
        "Grid": [
          ["N3", "N3", "N3"],
          ["NV", "NV", "N3"]
        ]
      },
      {
        "Grid": [
          ["N4", "N4", "NV"],
          ["NV", "N4", "N4"]
        ]
      },
      {
        "Grid": [
          ["NV", "N6", "N6"],
          ["N6", "N6", "NV"]
        ]
      }
    ]
  },
  "008-ro-mo": {
    "Grid": [
      ["M3", "M3", "M3", "M3", "M3", "M3"],
      ["M3", "M6", "M6", "M6", "M3", "M3"],
      ["M3", "M6", "NV", "NV", "M3", "M3"],
      ["M3", "M6", "NV", "NV", "M6", "M3"],
      ["M3", "M6", "M6", "M6", "M6", "M3"],
      ["M3", "M3", "M3", "M3", "M3", "M3"]
    ],
    "Pieces": [
      {
        "Grid": [
          ["N3", "NV"],
          ["N3", "N3"],
          ["NV", "N3"]
        ]
      },
      {
        "Grid": [
          ["N6", "N3"],
          ["N6", "N3"],
          ["NV", "N3"]
        ]
      },
      {
        "Grid": [
          ["NV", "N3"],
          ["N3", "N3"]
        ]
      },
      {
        "Grid": [
          ["N3", "N6", "N3"],
          ["N3", "NV", "NV"]
        ]
      },
      {
        "Grid": [
          ["N3", "N3", "N3"],
          ["N3", "NV", "NV"]
        ]
      },
      {
        "Grid": [
          ["N6", "N6", "N6"],
          ["NV", "NV", "N6"]
        ]
      },
      {
        "Grid": [
          ["N6", "NV"],
          ["N3", "N3"]
        ]
      },
      {
        "Grid": [
          ["NV", "N6", "N6"],
          ["N3", "N3", "NV"]
        ]
      },
      {
        "Grid": [
          ["N3", "NV", "NV"],
          ["N6", "N6", "NV"],
          ["NV", "N3", "N3"]
        ]
      }
    ]
  }
}
